setup.py
Ex/__init__.py
Ex/cmd.py
remote_shell.egg-info/PKG-INFO
remote_shell.egg-info/SOURCES.txt
remote_shell.egg-info/dependency_links.txt
remote_shell.egg-info/entry_points.txt
remote_shell.egg-info/not-zip-safe
remote_shell.egg-info/requires.txt
remote_shell.egg-info/top_level.txt