Metadata-Version: 1.0
Name: remote-shell
Version: 0.1
Summary: a tools exc in remotes server
Home-page: https://github.com/Qingluan/.git
Author: Qing luan
Author-email: darkhackdevil@gmail.com
License: MIT
Platform: UNKNOWN
